aliyunrdsbkp/__init__.py
aliyunrdsbkp/cleaner.py
aliyunrdsbkp/config.py
aliyunrdsbkp/db_file.py
aliyunrdsbkp/logger.py
aliyunrdsbkp/mysql_backup.py
aliyunrdsbkp/postman.py
aliyunrdsbkp/rds_instance.py
aliyunrdsbkp/scheduler.py
aliyun_rds_bkp-0.1.6.dist-info/LICENSE
aliyun_rds_bkp-0.1.6.dist-info/METADATA
aliyun_rds_bkp-0.1.6.dist-info/WHEEL
aliyun_rds_bkp-0.1.6.dist-info/top_level.txt
aliyun_rds_bkp-0.1.6.dist-info/RECORD
